topcast/__init__.py
topcast/cutter.py
topcast/models.py
topcast/topcaster.py
topcast/tts_item.py
topcast/chatgpt_themes/__init__.py
topcast/chatgpt_themes/base.py
topcast/chatgpt_themes/conclusion.py
topcast/chatgpt_themes/interview.py
topcast/chatgpt_themes/introduction.py
topcast/chatgpt_themes/none_theme.py
topcast/chatgpt_themes/summary.py
topcast/tts_providers/__init__.py
topcast/tts_providers/base.py
topcast/tts_providers/cgpt.py
topcast/tts_providers/elevenlabs.py
topcast/tts_providers/gcp.py
topcast/tts_providers/gt.py
topcast-0.1.8.dist-info/LICENSE.txt
topcast-0.1.8.dist-info/METADATA
topcast-0.1.8.dist-info/WHEEL
topcast-0.1.8.dist-info/top_level.txt
topcast-0.1.8.dist-info/RECORD
