Metadata-Version: 2.1
Name: topcast
Version: 0.1.8
Summary: A Python package for Topcast
Home-page: https://github.com/gormlabenz/topcast
Author: Gorm Labenz
Author-email: gorm@labenz.io
License: MIT
Keywords: topcast tts text-to-speech gcp google openai elevenlabs
Classifier: Development Status :: 3 - Alpha
Classifier: Intended Audience :: Developers
Classifier: License :: OSI Approved :: MIT License
Classifier: Operating System :: OS Independent
Classifier: Programming Language :: Python :: 3
Classifier: Programming Language :: Python :: 3.7
Classifier: Programming Language :: Python :: 3.8
Classifier: Programming Language :: Python :: 3.9
Requires-Python: >=3.7
License-File: LICENSE.txt
Requires-Dist: openai
Requires-Dist: protobuf
Requires-Dist: pydantic
Requires-Dist: pydub
Requires-Dist: elevenlabs
Requires-Dist: google-cloud-texttospeech
Requires-Dist: gTTS
Requires-Dist: annotated-types
Requires-Dist: anyio
Requires-Dist: build
Requires-Dist: cachetools
Requires-Dist: certifi
Requires-Dist: charset-normalizer
Requires-Dist: click
Requires-Dist: distro
Requires-Dist: google-api-core
Requires-Dist: google-auth
Requires-Dist: google-cloud-speech
Requires-Dist: googleapis-common-protos
Requires-Dist: grpcio
Requires-Dist: grpcio-status
Requires-Dist: h11
Requires-Dist: httpcore
Requires-Dist: httpx
Requires-Dist: idna
Requires-Dist: jiter
Requires-Dist: packaging
Requires-Dist: pip-tools
Requires-Dist: proto-plus
Requires-Dist: pyasn1
Requires-Dist: pyasn1-modules
Requires-Dist: pydantic-core
Requires-Dist: pyproject-hooks
Requires-Dist: requests
Requires-Dist: rsa
Requires-Dist: sniffio
Requires-Dist: tqdm
Requires-Dist: typing-extensions
Requires-Dist: urllib3
Requires-Dist: websockets
